writer_cm/__init__.py
writer_cm/py.typed
writer_cm/writer_cm.py
writer_cm-1.1.1.dist-info/WHEEL
writer_cm-1.1.1.dist-info/METADATA
writer_cm-1.1.1.dist-info/RECORD
