Metadata-Version: 2.1
Name: writer-cm
Version: 1.1.1
Summary: Atomically write files using a context manager
Home-page: https://github.com/dycw/writer-cm
License: MIT
Author: Derek Wan
Author-email: d.wan@icloud.com
Requires-Python: >=3.7,<4.0
Classifier: License :: OSI Approved :: MIT License
Classifier: Programming Language :: Python :: 3
Classifier: Programming Language :: Python :: 3.10
Classifier: Programming Language :: Python :: 3.7
Classifier: Programming Language :: Python :: 3.8
Classifier: Programming Language :: Python :: 3.9
Requires-Dist: atomicwrites (>=1.4.0,<2.0.0)
